rcquant_sdk/__init__.py
rcquant_sdk/api.py
rcquant_sdk/client.py
rcquant_sdk/findata_client.py
rcquant_sdk/interface.py
rcquant_sdk/listener.py
rcquant_sdk/tsocket.py
rcquant_sdk/data/__init__.py
rcquant_sdk/data/login_data.py
rcquant_sdk/data/message_data.py
rcquant_sdk/data/chart/__init__.py
rcquant_sdk/data/chart/bar_graph_param_data.py
rcquant_sdk/data/chart/base_graph_param_data.py
rcquant_sdk/data/chart/chart_init_param_data.py
rcquant_sdk/data/chart/financial_graph_param_data.py
rcquant_sdk/data/chart/graph_value_data.py
rcquant_sdk/data/chart/graph_value_list_data.py
rcquant_sdk/data/chart/legend_item_param_data.py
rcquant_sdk/data/chart/line_graph_param_data.py
rcquant_sdk/data/chart/marker_graph_param_data.py
rcquant_sdk/data/chart/ohlc_value_data.py
rcquant_sdk/data/chart/ohlc_value_list_data.py
rcquant_sdk/data/chart/plot_param_data.py
rcquant_sdk/data/chart/select_rect_param_data.py
rcquant_sdk/data/chart/text_graph_param_data.py
rcquant_sdk/data/chart/time_axis_param_data.py
rcquant_sdk/data/chart/time_span_gvlist_data.py
rcquant_sdk/data/chart/value_axis_param_data.py
rcquant_sdk/data/market/__init__.py
rcquant_sdk/data/market/fin_persist_delete_param_data.py
rcquant_sdk/data/market/fin_persist_filed_data.py
rcquant_sdk/data/market/fin_persist_read_param_data.py
rcquant_sdk/data/market/fin_persist_save_param_data.py
rcquant_sdk/data/market/history_ohlc_param_data.py
rcquant_sdk/data/market/history_tick_param_data.py
rcquant_sdk/data/market/market_param_data.py
rcquant_sdk/data/market/ohlc_data.py
rcquant_sdk/data/market/query_param_data.py
rcquant_sdk/data/market/sub_ohlc_param_data.py
rcquant_sdk/data/market/tick_data.py
rcquant_sdk/data/trade/__init__.py
rcquant_sdk/data/trade/account_data.py
rcquant_sdk/data/trade/db_vacuum_param_data.py
rcquant_sdk/data/trade/exc_product_data.py
rcquant_sdk/data/trade/exc_product_time_data.py
rcquant_sdk/data/trade/financial_filed_data.py
rcquant_sdk/data/trade/get_account_param_data.py
rcquant_sdk-0.0.250925.16.dist-info/METADATA
rcquant_sdk-0.0.250925.16.dist-info/WHEEL
rcquant_sdk-0.0.250925.16.dist-info/top_level.txt
rcquant_sdk-0.0.250925.16.dist-info/RECORD
