Metadata-Version: 2.1
Name: rcquant-sdk
Version: 0.0.250925.16
Summary: rcquant_sdk
Home-page: UNKNOWN
Author: rcquant_sdk
Author-email: rcquant_sdk@example.com
License: UNKNOWN
Platform: UNKNOWN
Classifier: Programming Language :: Python :: 3
Classifier: License :: OSI Approved :: MIT License
Classifier: Operating System :: OS Independent
Requires-Python: >=3.6
Requires-Dist: msgpack
Requires-Dist: numpy
Requires-Dist: pandas
